comet.py
comet/__init__.py
comet/comet.py
comet/config.py
comet/parallel.py
comet/parallel_terraform.py
comet/terraform.py
pycomet-0.0.6.dist-info/METADATA
pycomet-0.0.6.dist-info/WHEEL
pycomet-0.0.6.dist-info/entry_points.txt
pycomet-0.0.6.dist-info/top_level.txt
pycomet-0.0.6.dist-info/RECORD
