Metadata-Version: 2.1
Name: pycomet
Version: 0.0.6
Summary: A CLI tool to manage Terraform Components
Home-page: https://github.com/CodeSherpas/comet
Author: Gabe Levasseur
Author-email: gabriel.m.levasseur@gmail.com
License: UNKNOWN
Platform: UNKNOWN
Classifier: Programming Language :: Python :: 3
Classifier: License :: OSI Approved :: MIT License
Classifier: Operating System :: OS Independent
Requires-Dist: Click
Requires-Dist: pyyaml
Requires-Dist: pystache
Requires-Dist: jsonschema
Requires-Dist: python-terraform
